MANIFEST.in
README.txt
setup.cfg
setup.py
docs/HISTORY.txt
docs/INSTALL.txt
docs/LICENSE.GPL
docs/LICENSE.txt
plonetheme/__init__.py
plonetheme/__init__.pyc
plonetheme.INTKmodern.egg-info/PKG-INFO
plonetheme.INTKmodern.egg-info/SOURCES.txt
plonetheme.INTKmodern.egg-info/dependency_links.txt
plonetheme.INTKmodern.egg-info/entry_points.txt
plonetheme.INTKmodern.egg-info/namespace_packages.txt
plonetheme.INTKmodern.egg-info/not-zip-safe
plonetheme.INTKmodern.egg-info/requires.txt
plonetheme.INTKmodern.egg-info/top_level.txt
plonetheme/intkModern/__init__.py
plonetheme/intkModern/__init__.pyc
plonetheme/intkModern/configure.zcml
plonetheme/intkModern/tests.py
plonetheme/intkModern/browser/__init__.py
plonetheme/intkModern/browser/__init__.pyc
plonetheme/intkModern/browser/configure.zcml
plonetheme/intkModern/browser/interfaces.py
plonetheme/intkModern/browser/interfaces.pyc
plonetheme/intkModern/browser/mediaShow.pyc
plonetheme/intkModern/browser/views.py
plonetheme/intkModern/browser/views.pyc
plonetheme/intkModern/browser/templates/collection_custom.pt
plonetheme/intkModern/browser/templates/footer.pt
plonetheme/intkModern/browser/templates/managefooter.pt
plonetheme/intkModern/profiles/default/browserlayer.xml
plonetheme/intkModern/profiles/default/cssregistry.xml
plonetheme/intkModern/profiles/default/metadata.xml
plonetheme/intkModern/profiles/default/portlets.xml
plonetheme/intkModern/profiles/default/skins.xml
plonetheme/intkModern/profiles/default/theme.xml
plonetheme/intkModern/profiles/default/viewlets.xml
plonetheme/intkModern/profiles/default/types/Collection.xml
plonetheme/intkModern/skins/intkModern_custom/main_template.pt
plonetheme/intkModern/static/css/enhancements.css
plonetheme/intkModern/static/css/foundation.css
plonetheme/intkModern/static/css/intk.css
plonetheme/intkModern/static/css/reset.css
plonetheme/intkModern/static/css/screen.css
plonetheme/intkModern/static/images/favicon.ico
plonetheme/intkModern/static/images/logo.png
plonetheme/intkModern/static/images/preview.png
plonetheme/intkModern/static/js/main.js
plonetheme/intkModern/static/js/vendor/foundation.js
plonetheme/intkModern/static/js/vendor/jquery-1.11.1.min.js
plonetheme/intkModern/static/js/vendor/modernizr.js
plonetheme/intkModern/theme/index.html
plonetheme/intkModern/theme/manifest.cfg
plonetheme/intkModern/theme/rules.xml