Metadata-Version: 1.1
Name: plonetheme.INTKmodern
Version: 0.1.6
Summary: An installable Diazo theme for Plone 4
Home-page: https://github.com/intk/plonetheme.INTKmodern
Author: Andre Goncalves
Author-email: andre@intk.com
License: GPL
Download-URL: https://github.com/intk/plonetheme.INTKmodern/tarball/0.1.6
Platform: UNKNOWN
Classifier: Framework :: Plone
Classifier: Programming Language :: Python
